pyhesdm/__init__.py
pyhesdm/dmhalos.py
pyhesdm/dmhalos_layers_8Mpc.csv
pyhesdm/dmigm_layers_8Mpc.csv
pyhesdm/dmigm_std_layers_8Mpc.csv
pyhesdm/download.py
pyhesdm/dwarfs.csv
pyhesdm/hestia_dm.py
pyhesdm/model_lg_nside64.csv
pyhesdm/tully_groups.csv
pyhesdm-0.1.6.dist-info/licenses/LICENSE
pyhesdm-0.1.6.dist-info/METADATA
pyhesdm-0.1.6.dist-info/WHEEL
pyhesdm-0.1.6.dist-info/top_level.txt
pyhesdm-0.1.6.dist-info/RECORD
