Metadata-Version: 2.4
Name: pyhesdm
Version: 0.1.6
Summary: Local Universe Dispersion Measure Model Computed from HESTIA Simulation
Home-page: https://github.com/yuxinhuang1229/pyhesdm
Author: Yuxin Huang, Khee-Gan Lee, Noam Libeskind, Sunil Simha, Aurélien Valade and J. X. Prochaska
Author-email: mochafhxy@gmail.com
Classifier: Programming Language :: Python :: 3
Classifier: License :: OSI Approved :: MIT License
Classifier: Operating System :: OS Independent
Requires-Python: >=3.7
License-File: LICENSE
Requires-Dist: ne2001==0.0.1
Requires-Dist: dust_extinction==1.5
Requires-Dist: linetools==0.3.2
Requires-Dist: mwprop==1.0.10
Requires-Dist: importlib_resources
Requires-Dist: healpy==1.17.3
Dynamic: author
Dynamic: author-email
Dynamic: classifier
Dynamic: description
Dynamic: description-content-type
Dynamic: home-page
Dynamic: license-file
Dynamic: requires-dist
Dynamic: requires-python
Dynamic: summary
